decorating/__init__.py
decorating/animation.py
decorating/asciiart.py
decorating/base.py
decorating/color.py
decorating/debugging.py
decorating/decorator.py
decorating/general.py
decorating/monitor.py
decorating/stream.py
decorating-0.6.1.dist-info/DESCRIPTION.rst
decorating-0.6.1.dist-info/METADATA
decorating-0.6.1.dist-info/RECORD
decorating-0.6.1.dist-info/WHEEL
decorating-0.6.1.dist-info/metadata.json
decorating-0.6.1.dist-info/top_level.txt
