Metadata-Version: 2.0
Name: decorating
Version: 0.6.1
Summary: A useful collection of decorators (focused in animation)
Home-page: https://github.com/ryukinix/decorating
Author: Manoel Vilela
Author-email: manoel_vilela@engineer.com
License: MIT
Download-URL: https://github.com/ryukinix/decorating/archive/v0.6.1.tar.gz
Keywords: decorating animation decorators decorator
Platform: unix
Classifier: Environment :: Console
Classifier: Development Status :: 4 - Beta
Classifier: Topic :: Utilities
Classifier: Operating System :: Unix
Classifier: Programming Language :: Python :: 2.7
Classifier: Programming Language :: Python :: 3
Classifier: Programming Language :: Python :: 3.4
Classifier: Programming Language :: Python :: 3.5
Classifier: Programming Language :: Python :: 3.6
Provides-Extra: Requires-Dist
Requires-Dist: pypandoc; extra == 'Requires-Dist'
